cliconfig/__init__.py
cliconfig/_logger.py
cliconfig/_version.py
cliconfig/base.py
cliconfig/cli_parser.py
cliconfig/config_routines.py
cliconfig/dict_routines.py
cliconfig/process_routines.py
cliconfig/tag_routines.py
cliconfig/processing/__init__.py
cliconfig/processing/_ast_parser.py
cliconfig/processing/_type_parser.py
cliconfig/processing/allowed_functions.yaml
cliconfig/processing/base.py
cliconfig/processing/builtin.py
cliconfig/processing/create.py
cliconfig/yaml_tags/_yaml_tags.py
cliconfig-1.4.6.dist-info/licenses/LICENSE
cliconfig-1.4.6.dist-info/METADATA
cliconfig-1.4.6.dist-info/WHEEL
cliconfig-1.4.6.dist-info/top_level.txt
cliconfig-1.4.6.dist-info/RECORD
