Metadata-Version: 2.4
Name: cliconfig
Version: 1.4.6
Summary: Merge your config files and set parameters from the command line in a simple way.
Author-email: Valentin Goldite <valentin.goldite@gmail.com>
Project-URL: Source, https://github.com/valentingol/cliconfig
Keywords: cli,config,cliconfig,python,yaml,merge
Classifier: Programming Language :: Python :: 3
Requires-Python: >=3.7
License-File: LICENSE
Requires-Dist: flatten-dict
Requires-Dist: PyYAML
Dynamic: license-file
